{
  "_class": "group",
  "booleanOperation": 0,
  "clippingMaskMode": 0,
  "do_objectID": "6A06E9DF-0134-4BF6-80F4-2C6AD89FECE8",
  "exportOptions": {
    "_class": "exportOptions",
    "exportFormats": [
    ],
    "includedLayerIds": [
    ],
    "layerOptions": 0,
    "shouldTrim": false
  },
  "frame": {
    "_class": "rect",
    "constrainProportions": false,
    "height": 390,
    "width": 240,
    "x": 90,
    "y": 244
  },
  "hasClickThrough": false,
  "hasClippingMask": false,
  "isFixedToViewport": false,
  "isFlippedHorizontal": false,
  "isFlippedVertical": false,
  "isLocked": false,
  "isVisible": true,
  "layerListExpandedType": 0,
  "layers": [
    {
      "class": "group",
      "id": "482CBC1D-101D-4BD6-B10A-B28CDC3B1BEE"
    },
    {
      "class": "group",
      "id": "CECE8FD7-EFE1-42A7-B911-D0F4207CCABD"
    },
    {
      "class": "group",
      "id": "568D2874-6C36-4109-82DD-D1C1A2B1A62A"
    },
    {
      "class": "group",
      "id": "95618E17-0610-4174-983C-F13F93FDECA6"
    },
    {
      "class": "group",
      "id": "762E52BA-078A-4739-96E7-11CB152D04B3"
    },
    {
      "class": "group",
      "id": "5B9364A0-4507-40E5-9411-C2FD389E9CC5"
    },
    {
      "class": "group",
      "id": "BA3AB2F3-8FEA-434E-B4D7-2661E9E95956"
    }
  ],
  "name": "goods_list",
  "nameIsFixed": true,
  "resizingConstraint": 63,
  "resizingType": 0,
  "rotation": 0,
  "shouldBreakMaskChain": false,
  "style": {
    "_class": "style",
    "endMarkerType": 0,
    "miterLimit": 10,
    "startMarkerType": 0,
    "windingRule": 1
  }
}