{
  "_class": "group",
  "booleanOperation": 0,
  "clippingMaskMode": 0,
  "do_objectID": "2B5993E9-793B-4731-B0FC-001D7819C34D",
  "exportOptions": {
    "_class": "exportOptions",
    "exportFormats": [
    ],
    "includedLayerIds": [
    ],
    "layerOptions": 0,
    "shouldTrim": false
  },
  "frame": {
    "_class": "rect",
    "constrainProportions": false,
    "height": 310,
    "width": 168,
    "x": 143,
    "y": 240
  },
  "hasClickThrough": false,
  "hasClippingMask": false,
  "isFixedToViewport": false,
  "isFlippedHorizontal": false,
  "isFlippedVertical": false,
  "isLocked": false,
  "isVisible": true,
  "layerListExpandedType": 0,
  "layers": [
    {
      "class": "group",
      "id": "9E382FF8-41E4-4567-8A43-D0ECB7AEFBEF"
    },
    {
      "class": "group",
      "id": "E8EEC41C-A49F-4250-AF4C-E2DDD06777EA"
    },
    {
      "class": "group",
      "id": "24FCF5D1-0568-4B7B-8284-1381F1902880"
    },
    {
      "class": "group",
      "id": "D54773D9-410C-44CB-8B16-07D2EB349257"
    },
    {
      "class": "group",
      "id": "DCD23389-0B71-428E-9633-F9693E07D9B8"
    },
    {
      "class": "group",
      "id": "661C0541-AB76-4FFE-934F-5CE8EAE17CB0"
    },
    {
      "class": "group",
      "id": "2E938C5A-6F05-4140-9B7E-F1E07EA39D1D"
    },
    {
      "class": "group",
      "id": "DBA7885F-1982-4D51-A4E4-E2B623B723E1"
    }
  ],
  "name": "goods_list-block",
  "nameIsFixed": true,
  "resizingConstraint": 63,
  "resizingType": 0,
  "rotation": 0,
  "shouldBreakMaskChain": false,
  "style": {
    "_class": "style",
    "endMarkerType": 0,
    "miterLimit": 10,
    "startMarkerType": 0,
    "windingRule": 1
  }
}