{
  "_class": "group",
  "booleanOperation": 0,
  "clippingMaskMode": 0,
  "do_objectID": "0D6C0F23-B2EF-49D3-95B0-FBD8945E3BDB",
  "exportOptions": {
    "_class": "exportOptions",
    "exportFormats": [
    ],
    "includedLayerIds": [
    ],
    "layerOptions": 0,
    "shouldTrim": false
  },
  "frame": {
    "_class": "rect",
    "constrainProportions": false,
    "height": 60,
    "width": 360,
    "x": 0,
    "y": 580
  },
  "hasClickThrough": false,
  "hasClippingMask": false,
  "isFixedToViewport": false,
  "isFlippedHorizontal": false,
  "isFlippedVertical": false,
  "isLocked": false,
  "isVisible": true,
  "layerListExpandedType": 0,
  "layers": [
    {
      "class": "rectangle",
      "id": "AC5803A8-4768-4BD7-A12B-2376E5B66596"
    },
    {
      "class": "text",
      "id": "FDEFB8CB-7705-4FE0-9B03-D9B992E48E23"
    },
    {
      "class": "text",
      "id": "96539759-DAE3-445D-B0AA-BE66DE36D010"
    },
    {
      "class": "text",
      "id": "EA6C1DBC-4D85-4940-B85B-36BE5CFEC8DE"
    },
    {
      "class": "text",
      "id": "0828B680-3643-4FB1-A1FC-D0AA2A5CA3AD"
    },
    {
      "class": "group",
      "id": "30DC300A-8D1F-45FF-ABB7-3A4E82318BBA"
    },
    {
      "class": "symbolInstance",
      "id": "EFFBF0B5-9275-4583-8A29-D0C7399FC8C0"
    },
    {
      "class": "symbolInstance",
      "id": "81AD4575-A22E-4F0D-AF37-4B3295185770"
    },
    {
      "class": "group",
      "id": "975E5E57-EF8B-4B11-A2AF-BE3CF647612F"
    }
  ],
  "name": "tabs",
  "nameIsFixed": true,
  "resizingConstraint": 63,
  "resizingType": 0,
  "rotation": 0,
  "shouldBreakMaskChain": false,
  "style": {
    "_class": "style",
    "endMarkerType": 0,
    "miterLimit": 10,
    "startMarkerType": 0,
    "windingRule": 1
  }
}