{
  "_class": "group",
  "do_objectID": "B299CF86-61EF-4C54-B1B7-2CF0F56F5FF3",
  "exportOptions": {
    "_class": "exportOptions",
    "exportFormats": [
    ],
    "includedLayerIds": [
    ],
    "layerOptions": 0,
    "shouldTrim": false
  },
  "frame": {
    "_class": "rect",
    "constrainProportions": true,
    "height": 20,
    "width": 20,
    "x": 0,
    "y": 0
  },
  "hasClickThrough": false,
  "isFlippedHorizontal": false,
  "isFlippedVertical": false,
  "isLocked": false,
  "isVisible": true,
  "layerListExpandedType": 0,
  "layers": [
    {
      "class": "shapeGroup",
      "id": "CBB2DBD0-ACFB-4F40-9626-BDB63705C4F7"
    },
    {
      "class": "shapeGroup",
      "id": "754B174D-770C-4BCC-993A-C52B0EE4515B"
    },
    {
      "class": "shapeGroup",
      "id": "90781095-DCDD-4DEC-8425-FD5C05797684"
    },
    {
      "class": "shapeGroup",
      "id": "931529FE-E356-482F-AA61-139251EABA0F"
    },
    {
      "class": "shapeGroup",
      "id": "EC304E6D-9D97-4FE4-B25C-72059CBB192E"
    }
  ],
  "name": "微信",
  "nameIsFixed": false,
  "resizingConstraint": 63,
  "resizingType": 0,
  "rotation": 0,
  "shouldBreakMaskChain": false,
  "style": {
    "_class": "style",
    "endDecorationType": 0,
    "miterLimit": 10,
    "startDecorationType": 0
  }
}