{
  "_class": "shapeGroup",
  "clippingMaskMode": 0,
  "do_objectID": "F361337E-F13A-46EA-AE17-5C69BBC5A581",
  "exportOptions": {
    "_class": "exportOptions",
    "exportFormats": [
      {
        "_class": "exportFormat",
        "absoluteSize": 0,
        "fileFormat": "png",
        "name": "",
        "namingScheme": 0,
        "scale": 2,
        "visibleScaleType": 0
      }
    ],
    "includedLayerIds": [
    ],
    "layerOptions": 0,
    "shouldTrim": false
  },
  "frame": {
    "_class": "rect",
    "constrainProportions": false,
    "height": 50,
    "width": 60,
    "x": 250,
    "y": 498.3
  },
  "hasClickThrough": false,
  "hasClippingMask": false,
  "isFlippedHorizontal": false,
  "isFlippedVertical": false,
  "isLocked": false,
  "isVisible": true,
  "layerListExpandedType": 0,
  "layers": [
    {
      "class": "rectangle",
      "id": "E43B3794-12FC-465B-B605-6C5757273517"
    }
  ],
  "name": "064 Red Salvation",
  "nameIsFixed": true,
  "resizingConstraint": 63,
  "resizingType": 0,
  "rotation": 0,
  "shouldBreakMaskChain": false,
  "style": {
    "_class": "style",
    "blur": {
      "_class": "blur",
      "center": "{0.5, 0.5}",
      "isEnabled": false,
      "motionAngle": 0,
      "radius": 0.5,
      "type": 0
    },
    "endDecorationType": 0,
    "fills": [
      {
        "_class": "fill",
        "color": {
          "_class": "color",
          "alpha": 1,
          "blue": 0.847,
          "green": 0.847,
          "red": 0.847
        },
        "fillType": 1,
        "gradient": {
          "_class": "gradient",
          "elipseLength": 0,
          "from": "{0.5, 1}",
          "gradientType": 0,
          "stops": [
            {
              "_class": "gradientStop",
              "color": {
                "_class": "color",
                "alpha": 1,
                "blue": 0.2784313725490198,
                "green": 0.2313725490196079,
                "red": 0.9568627450980391
              },
              "position": 0
            },
            {
              "_class": "gradientStop",
              "color": {
                "_class": "color",
                "alpha": 1,
                "blue": 0.580392156862745,
                "green": 0.2274509803921568,
                "red": 0.2705882352941174
              },
              "position": 1
            }
          ],
          "to": "{0.5, 0}"
        },
        "isEnabled": true,
        "noiseIndex": 0,
        "noiseIntensity": 0,
        "patternFillType": 1,
        "patternTileScale": 1
      }
    ],
    "miterLimit": 10,
    "sharedObjectID": "076D36C3-4EF4-4024-A376-22B35679F8D4",
    "startDecorationType": 0
  },
  "windingRule": 1
}