{
  "_class": "shapeGroup",
  "clippingMaskMode": 0,
  "do_objectID": "F4ECA67D-D394-4F78-B243-7DB3CD9AA64E",
  "exportOptions": {
    "_class": "exportOptions",
    "exportFormats": [
    ],
    "includedLayerIds": [
    ],
    "layerOptions": 0,
    "shouldTrim": false
  },
  "frame": {
    "_class": "rect",
    "constrainProportions": false,
    "height": 90,
    "width": 360,
    "x": 0,
    "y": 0
  },
  "hasClickThrough": false,
  "hasClippingMask": false,
  "isFlippedHorizontal": false,
  "isFlippedVertical": false,
  "isLocked": false,
  "isVisible": true,
  "layerListExpandedType": 0,
  "layers": [
    {
      "class": "rectangle",
      "id": "B79AA9F5-EBF1-4788-BF6D-3383FBDAB997"
    }
  ],
  "name": "Rectangle 13",
  "nameIsFixed": false,
  "resizingConstraint": 63,
  "resizingType": 0,
  "rotation": 0,
  "shouldBreakMaskChain": false,
  "style": {
    "sharedObjectID": "80F9A3D3-DAD0-46D7-8368-4307752479B8"
  },
  "windingRule": 1
}