{
  "_class": "group",
  "do_objectID": "E085805E-B3EF-4854-B18D-57F2BE8B8E10",
  "exportOptions": {
    "_class": "exportOptions",
    "exportFormats": [
    ],
    "includedLayerIds": [
    ],
    "layerOptions": 0,
    "shouldTrim": false
  },
  "frame": {
    "_class": "rect",
    "constrainProportions": false,
    "height": 44,
    "width": 89,
    "x": 0,
    "y": 308
  },
  "hasClickThrough": false,
  "isFlippedHorizontal": false,
  "isFlippedVertical": false,
  "isLocked": false,
  "isVisible": true,
  "layerListExpandedType": 0,
  "layers": [
    {
      "class": "shapeGroup",
      "id": "7B2E5E7A-C5BD-4687-B827-68BD2D369C04"
    },
    {
      "class": "text",
      "id": "799995A2-9429-433A-A191-EAB5D1AEE254"
    }
  ],
  "name": "侧栏-item copy 7",
  "nameIsFixed": true,
  "resizingConstraint": 63,
  "resizingType": 0,
  "rotation": 0,
  "shouldBreakMaskChain": false,
  "style": {
    "_class": "style",
    "endDecorationType": 0,
    "miterLimit": 10,
    "startDecorationType": 0
  }
}